stubbingmytoe/__init__.py
stubbingmytoe/extractor.py
stubbingmytoe/color_extractor/__init__.py
stubbingmytoe/color_extractor/extractor.py
stubbingmytoe-0.1.10.dist-info/LICENSE
stubbingmytoe-0.1.10.dist-info/METADATA
stubbingmytoe-0.1.10.dist-info/WHEEL
stubbingmytoe-0.1.10.dist-info/entry_points.txt
stubbingmytoe-0.1.10.dist-info/top_level.txt
stubbingmytoe-0.1.10.dist-info/RECORD
