Metadata-Version: 2.1
Name: stubbingmytoe
Version: 0.1.10
Summary: A package that includes various tools, including a color extractor
Home-page: https://github.com/macturnerr2002/stubbingmytoe
Author: macturner
Author-email: mac@stubbingmytoe.ca
Classifier: Programming Language :: Python :: 3
Classifier: License :: OSI Approved :: MIT License
Classifier: Operating System :: OS Independent
Requires-Python: >=3.6
License-File: LICENSE
Requires-Dist: opencv-python
Requires-Dist: numpy
Requires-Dist: scikit-learn
Requires-Dist: tqdm
Requires-Dist: matplotlib
Requires-Dist: jinja2
